doomarena/taubench/__init__.py
doomarena/taubench/adversarial_user.py
doomarena/taubench/attack_gateway.py
doomarena/taubench/data/airline_classification.json
doomarena/taubench/data/retail_classification.json
doomarena/taubench/data/sample_airline.json
doomarena/taubench/filters/is_get_product_details_action_filter.py
doomarena/taubench/filters/is_respond_action_filter.py
doomarena/taubench/scripts/analyze_attack_results.py
doomarena/taubench/scripts/attack_script.py
doomarena/taubench/success_filters/airline_info_leak_success_filter.py
doomarena/taubench/success_filters/llm_judge.py
doomarena/taubench/success_filters/retail_refund_success_filter.py
doomarena/taubench/success_filters/retail_secrets_success_filter.py
doomarena/taubench/success_filters/send_certificate_success_filters.py
doomarena/taubench/system_prompt_config/system_prompt_initialization.py
doomarena/taubench/system_prompt_config/utils.py
doomarena/taubench/system_prompt_config/dan_mode/dan_mode_airline.txt
doomarena/taubench/system_prompt_config/dan_mode/dan_mode_retail.txt
doomarena/taubench/system_prompt_config/dan_mode/dan_mode_retaildb.txt
doomarena/taubench/system_prompt_config/few_shot_examples/airline_few_shot.json
doomarena/taubench/system_prompt_config/few_shot_examples/retail_few_shot.json
doomarena/taubench/system_prompt_config/few_shot_examples/retaildb_few_shot.json
doomarena/taubench/system_prompt_config/tools/airline_tools.json
doomarena/taubench/system_prompt_config/tools/retail_tools.json
doomarena_taubench-0.0.4.dist-info/METADATA
doomarena_taubench-0.0.4.dist-info/WHEEL
doomarena_taubench-0.0.4.dist-info/top_level.txt
doomarena_taubench-0.0.4.dist-info/RECORD
